{"error": false, "size": [1280, 720], "name": "Fundamental Paper Novel", "version": "FULLY_RECRAFTED", "location": {"label": {}, "define": {"all_achievements": ["game/achievements.rpy", 516], "gui.accent_color": ["game/gui.rpy", 26], "gui.idle_color": ["game/gui.rpy", 29], "gui.idle_small_color": ["game/gui.rpy", 33], "gui.hover_color": ["game/gui.rpy", 36], "gui.selected_color": ["game/gui.rpy", 40], "gui.insensitive_color": ["game/gui.rpy", 43], "gui.muted_color": ["game/gui.rpy", 47], "gui.hover_muted_color": ["game/gui.rpy", 48], "gui.text_color": ["game/gui.rpy", 51], "gui.interface_text_color": ["game/gui.rpy", 52], "gui.name_text_outlines": ["game/gui.rpy", 54], "gui.text_font": ["game/gui.rpy", 60], "gui.name_text_font": ["game/gui.rpy", 63], "gui.interface_text_font": ["game/gui.rpy", 66], "gui.text_size": ["game/gui.rpy", 69], "gui.name_text_size": ["game/gui.rpy", 72], "gui.interface_text_size": ["game/gui.rpy", 75], "gui.label_text_size": ["game/gui.rpy", 78], "gui.notify_text_size": ["game/gui.rpy", 81], "gui.title_text_size": ["game/gui.rpy", 84], "gui.main_menu_background": ["game/gui.rpy", 90], "gui.game_menu_background": ["game/gui.rpy", 91], "gui.textbox_height": ["game/gui.rpy", 100], "gui.textbox_yalign": ["game/gui.rpy", 104], "gui.name_xpos": ["game/gui.rpy", 109], "gui.name_ypos": ["game/gui.rpy", 110], "gui.name_xalign": ["game/gui.rpy", 114], "gui.namebox_width": ["game/gui.rpy", 118], "gui.namebox_height": ["game/gui.rpy", 119], "gui.namebox_borders": ["game/gui.rpy", 123], "gui.namebox_tile": ["game/gui.rpy", 127], "gui.dialogue_xpos": ["game/gui.rpy", 133], "gui.dialogue_ypos": ["game/gui.rpy", 134], "gui.dialogue_width": ["game/gui.rpy", 137], "gui.dialogue_text_xalign": ["game/gui.rpy", 141], "gui.button_width": ["game/gui.rpy", 150], "gui.button_height": ["game/gui.rpy", 151], "gui.button_borders": ["game/gui.rpy", 154], "gui.button_tile": ["game/gui.rpy", 158], "gui.button_text_font": ["game/gui.rpy", 161], "gui.button_text_size": ["game/gui.rpy", 164], "gui.button_text_idle_color": ["game/gui.rpy", 167], "gui.button_text_hover_color": ["game/gui.rpy", 168], "gui.button_text_selected_color": ["game/gui.rpy", 169], "gui.button_text_insensitive_color": ["game/gui.rpy", 170], "gui.button_text_xalign": ["game/gui.rpy", 174], "gui.radio_button_borders": ["game/gui.rpy", 183], "gui.check_button_borders": ["game/gui.rpy", 185], "gui.confirm_button_text_xalign": ["game/gui.rpy", 187], "gui.page_button_borders": ["game/gui.rpy", 189], "gui.quick_button_borders": ["game/gui.rpy", 191], "gui.quick_button_text_size": ["game/gui.rpy", 192], "gui.quick_button_text_idle_color": ["game/gui.rpy", 193], "gui.quick_button_text_selected_color": ["game/gui.rpy", 194], "gui.choice_button_width": ["game/gui.rpy", 207], "gui.choice_button_height": ["game/gui.rpy", 208], "gui.choice_button_tile": ["game/gui.rpy", 209], "gui.choice_button_borders": ["game/gui.rpy", 210], "gui.choice_button_text_font": ["game/gui.rpy", 211], "gui.choice_button_text_size": ["game/gui.rpy", 212], "gui.choice_button_text_xalign": ["game/gui.rpy", 213], "gui.choice_button_text_idle_color": ["game/gui.rpy", 214], "gui.choice_button_text_hover_color": ["game/gui.rpy", 215], "gui.choice_button_text_insensitive_color": ["game/gui.rpy", 216], "gui.slot_button_width": ["game/gui.rpy", 226], "gui.slot_button_height": ["game/gui.rpy", 227], "gui.slot_button_borders": ["game/gui.rpy", 228], "gui.slot_button_text_size": ["game/gui.rpy", 229], "gui.slot_button_text_xalign": ["game/gui.rpy", 230], "gui.slot_button_text_idle_color": ["game/gui.rpy", 231], "gui.slot_button_text_selected_idle_color": ["game/gui.rpy", 232], "gui.slot_button_text_selected_hover_color": ["game/gui.rpy", 233], "config.thumbnail_width": ["game/gui.rpy", 236], "config.thumbnail_height": ["game/gui.rpy", 237], "gui.file_slot_cols": ["game/gui.rpy", 240], "gui.file_slot_rows": ["game/gui.rpy", 241], "gui.navigation_xpos": ["game/gui.rpy", 251], "gui.skip_ypos": ["game/gui.rpy", 254], "gui.notify_ypos": ["game/gui.rpy", 257], "gui.choice_spacing": ["game/gui.rpy", 260], "gui.navigation_spacing": ["game/gui.rpy", 263], "gui.pref_spacing": ["game/gui.rpy", 266], "gui.pref_button_spacing": ["game/gui.rpy", 269], "gui.page_spacing": ["game/gui.rpy", 272], "gui.slot_spacing": ["game/gui.rpy", 275], "gui.main_menu_text_xalign": ["game/gui.rpy", 278], "gui.frame_borders": ["game/gui.rpy", 287], "gui.confirm_frame_borders": ["game/gui.rpy", 290], "gui.skip_frame_borders": ["game/gui.rpy", 293], "gui.notify_frame_borders": ["game/gui.rpy", 296], "gui.frame_tile": ["game/gui.rpy", 299], "gui.bar_size": ["game/gui.rpy", 311], "gui.scrollbar_size": ["game/gui.rpy", 312], "gui.slider_size": ["game/gui.rpy", 313], "gui.bar_tile": ["game/gui.rpy", 316], "gui.scrollbar_tile": ["game/gui.rpy", 317], "gui.slider_tile": ["game/gui.rpy", 318], "gui.bar_borders": ["game/gui.rpy", 321], "gui.scrollbar_borders": ["game/gui.rpy", 322], "gui.slider_borders": ["game/gui.rpy", 323], "gui.vbar_borders": ["game/gui.rpy", 326], "gui.vscrollbar_borders": ["game/gui.rpy", 327], "gui.vslider_borders": ["game/gui.rpy", 328], "gui.unscrollable": ["game/gui.rpy", 332], "config.history_length": ["game/gui.rpy", 340], "gui.history_height": ["game/gui.rpy", 344], "gui.history_name_xpos": ["game/gui.rpy", 348], "gui.history_name_ypos": ["game/gui.rpy", 349], "gui.history_name_width": ["game/gui.rpy", 350], "gui.history_name_xalign": ["game/gui.rpy", 351], "gui.history_text_xpos": ["game/gui.rpy", 354], "gui.history_text_ypos": ["game/gui.rpy", 355], "gui.history_text_width": ["game/gui.rpy", 356], "gui.history_text_xalign": ["game/gui.rpy", 357], "gui.nvl_borders": ["game/gui.rpy", 365], "gui.nvl_list_length": ["game/gui.rpy", 369], "gui.nvl_height": ["game/gui.rpy", 373], "gui.nvl_spacing": ["game/gui.rpy", 377], "gui.nvl_name_xpos": ["game/gui.rpy", 381], "gui.nvl_name_ypos": ["game/gui.rpy", 382], "gui.nvl_name_width": ["game/gui.rpy", 383], "gui.nvl_name_xalign": ["game/gui.rpy", 384], "gui.nvl_text_xpos": ["game/gui.rpy", 387], "gui.nvl_text_ypos": ["game/gui.rpy", 388], "gui.nvl_text_width": ["game/gui.rpy", 389], "gui.nvl_text_xalign": ["game/gui.rpy", 390], "gui.nvl_thought_xpos": ["game/gui.rpy", 394], "gui.nvl_thought_ypos": ["game/gui.rpy", 395], "gui.nvl_thought_width": ["game/gui.rpy", 396], "gui.nvl_thought_xalign": ["game/gui.rpy", 397], "gui.nvl_button_xpos": ["game/gui.rpy", 400], "gui.nvl_button_xalign": ["game/gui.rpy", 401], "gui.language": ["game/gui.rpy", 409], "config.narrator_menu": ["game/screens.rpy", 219], "quick_menu": ["game/screens.rpy", 273], "gui.history_allow_tags": ["game/screens.rpy", 950], "config.nvl_list_length": ["game/screens.rpy", 1380], "onscreen_achievements": ["game/achievement_backend.rpy", 475], "config.allow_underfull_grids": ["game/achievement_backend.rpy", 478], "myconfig.INGAME_POPUP_WITH_STEAM": ["game/achievements.rpy", 44], "myconfig.ACHIEVEMENT_HIDE_TIME": ["game/achievements.rpy", 47], "myconfig.SHOW_ACHIEVEMENT_POPUPS": ["game/achievements.rpy", 51], "myconfig.ACHIEVEMENT_SOUND": ["game/achievements.rpy", 54], "myconfig.ACHIEVEMENT_CHANNEL": ["game/achievements.rpy", 58], "myconfig.ACHIEVEMENT_CALLBACK": ["game/achievements.rpy", 64], "welcome_achievement": ["game/achievements.rpy", 95], "playedonce": ["game/achievements.rpy", 117], "lonelyend": ["game/achievements.rpy", 126], "clairesend": ["game/achievements.rpy", 135], "engelsend": ["game/achievements.rpy", 144], "bubblesend": ["game/achievements.rpy", 153], "lanasend": ["game/achievements.rpy", 162], "abbiesend": ["game/achievements.rpy", 171], "oligangsend": ["game/achievements.rpy", 180], "cubbiesend": ["game/achievements.rpy", 189], "kevinsend": ["game/achievements.rpy", 198], "popularsend": ["game/achievements.rpy", 207], "robrileysend": ["game/achievements.rpy", 216], "rubysend": ["game/achievements.rpy", 225], "skellsend": ["game/achievements.rpy", 234], "circlesend": ["game/achievements.rpy", 243], "thavelsend": ["game/achievements.rpy", 252], "bloomiesend": ["game/achievements.rpy", 261], "emilysend": ["game/achievements.rpy", 270], "demisend": ["game/achievements.rpy", 279], "sashasend": ["game/achievements.rpy", 288], "disksend": ["game/achievements.rpy", 297], "quinnsend": ["game/achievements.rpy", 306], "mattesend": ["game/achievements.rpy", 315], "jamsend": ["game/achievements.rpy", 324], "sparksend": ["game/achievements.rpy", 333], "temerosend": ["game/achievements.rpy", 342], "yinhuisend": ["game/achievements.rpy", 351], "yangyisend": ["game/achievements.rpy", 360], "yinyangend": ["game/achievements.rpy", 369], "noxsend": ["game/achievements.rpy", 378], "carmensend": ["game/achievements.rpy", 387], "koasend": ["game/achievements.rpy", 396], "orchidsend": ["game/achievements.rpy", 405], "jacobsend": ["game/achievements.rpy", 414], "pythonsend": ["game/achievements.rpy", 423], "aboutpage": ["game/notallowednames.rpy", 3], "notusablenames": ["game/notallowednames.rpy", 4], "config.name": ["game/options.rpy", 15], "gui.show_name": ["game/options.rpy", 21], "config.version": ["game/options.rpy", 26], "gui.about": ["game/options.rpy", 32], "build.name": ["game/options.rpy", 54], "config.has_sound": ["game/options.rpy", 63], "config.has_music": ["game/options.rpy", 64], "config.has_voice": ["game/options.rpy", 65], "config.main_menu_music": ["game/options.rpy", 79], "config.enter_transition": ["game/options.rpy", 90], "config.exit_transition": ["game/options.rpy", 91], "config.intra_transition": ["game/options.rpy", 96], "config.after_load_transition": ["game/options.rpy", 101], "config.end_game_transition": ["game/options.rpy", 106], "config.window": ["game/options.rpy", 123], "config.window_show_transition": ["game/options.rpy", 128], "config.window_hide_transition": ["game/options.rpy", 129], "config.save_directory": ["game/options.rpy", 160], "config.window_icon": ["game/options.rpy", 167], "config.mouse": ["game/options.rpy", 225], "clairelv": ["game/requirements.rpy", 3], "engellv": ["game/requirements.rpy", 4], "bubblelv": ["game/requirements.rpy", 5], "lanalv": ["game/requirements.rpy", 6], "abbielv": ["game/requirements.rpy", 7], "oliganglv": ["game/requirements.rpy", 8], "popularlv": ["game/requirements.rpy", 9], "cubbielv": ["game/requirements.rpy", 10], "kevinlv": ["game/requirements.rpy", 11], "robbrileylv": ["game/requirements.rpy", 12], "rubylv": ["game/requirements.rpy", 13], "skelllv": ["game/requirements.rpy", 14], "circlelv": ["game/requirements.rpy", 16], "thavellv": ["game/requirements.rpy", 17], "bloomielv": ["game/requirements.rpy", 18], "gracelv": ["game/requirements.rpy", 19], "sashalv": ["game/requirements.rpy", 20], "demilv": ["game/requirements.rpy", 21], "emilylv": ["game/requirements.rpy", 22], "disklv": ["game/requirements.rpy", 25], "quinnlv": ["game/requirements.rpy", 26], "temerolv": ["game/requirements.rpy", 27], "sparklv": ["game/requirements.rpy", 28], "noxlv": ["game/requirements.rpy", 29], "koalv": ["game/requirements.rpy", 30], "jacoblv": ["game/requirements.rpy", 31], "yinhuilv": ["game/requirements.rpy", 32], "yangyilv": ["game/requirements.rpy", 33], "carmenlv": ["game/requirements.rpy", 34], "jamlv": ["game/requirements.rpy", 35], "mattelv": ["game/requirements.rpy", 36], "orchidlv": ["game/requirements.rpy", 37], "claireending": ["game/requirements.rpy", 41], "engelending": ["game/requirements.rpy", 42], "bubbleending": ["game/requirements.rpy", 43], "lanaending": ["game/requirements.rpy", 44], "abbieending": ["game/requirements.rpy", 45], "oligangending": ["game/requirements.rpy", 46], "circlending": ["game/requirements.rpy", 47], "thravelending": ["game/requirements.rpy", 48], "bloomieending": ["game/requirements.rpy", 49], "lonelyending": ["game/requirements.rpy", 50], "kind": ["game/requirements.rpy", 54], "mean": ["game/requirements.rpy", 55], "calm": ["game/requirements.rpy", 56], "claireknow": ["game/requirements.rpy", 60], "engelknow": ["game/requirements.rpy", 61], "abbieknow": ["game/requirements.rpy", 62], "lanaknow": ["game/requirements.rpy", 63], "bubbleknow": ["game/requirements.rpy", 64], "oligangknow": ["game/requirements.rpy", 65], "skellknow": ["game/requirements.rpy", 66], "rubyknow": ["game/requirements.rpy", 67], "robbyknow": ["game/requirements.rpy", 68], "rileyknow": ["game/requirements.rpy", 69], "popularknow": ["game/requirements.rpy", 70], "cubbieknow": ["game/requirements.rpy", 71], "kevinknow": ["game/requirements.rpy", 72], "diskknow": ["game/requirements.rpy", 74], "quinnknow": ["game/requirements.rpy", 75], "temeroknow": ["game/requirements.rpy", 76], "sparkknow": ["game/requirements.rpy", 77], "noxknow": ["game/requirements.rpy", 78], "koaknow": ["game/requirements.rpy", 79], "miaknow": ["game/requirements.rpy", 80], "jexknow": ["game/requirements.rpy", 81], "pythonknow": ["game/requirements.rpy", 82], "carmenknow": ["game/requirements.rpy", 83], "jamknow": ["game/requirements.rpy", 84], "matteknow": ["game/requirements.rpy", 85], "jacobknow": ["game/requirements.rpy", 86], "notiveknow": ["game/requirements.rpy", 87], "orchidknow": ["game/requirements.rpy", 88], "yinhuiknow": ["game/requirements.rpy", 89], "yangyiknow": ["game/requirements.rpy", 90], "pythonchallenge": ["game/requirements.rpy", 92], "pythoncode4": ["game/requirements.rpy", 93], "pythoncode2": ["game/requirements.rpy", 94], "pythoncode0": ["game/requirements.rpy", 95], "diskparty": ["game/requirements.rpy", 96], "yinhuiparty": ["game/requirements.rpy", 98], "yangyiparty": ["game/requirements.rpy", 99], "yinyangparty": ["game/requirements.rpy", 100], "yinhuiend": ["game/requirements.rpy", 101], "yangyiend": ["game/requirements.rpy", 102], "quinnshowsee": ["game/requirements.rpy", 104], "diqutte": ["game/requirements.rpy", 106], "spatemnox": ["game/requirements.rpy", 107], "jamorcar": ["game/requirements.rpy", 108], "koamiajex": ["game/requirements.rpy", 109], "jacnotyinyang": ["game/requirements.rpy", 110], "jamsnitch": ["game/requirements.rpy", 112], "jamcomfort": ["game/requirements.rpy", 113], "carmencomfort": ["game/requirements.rpy", 114], "temerolistenin": ["game/requirements.rpy", 115], "sparklistenin": ["game/requirements.rpy", 116], "temeroformseen": ["game/requirements.rpy", 117], "sparkformseen": ["game/requirements.rpy", 118], "circleknow": ["game/requirements.rpy", 120], "thavelknow": ["game/requirements.rpy", 121], "bloomieknow": ["game/requirements.rpy", 122], "emilyknow": ["game/requirements.rpy", 123], "demiknow": ["game/requirements.rpy", 124], "sashaknow": ["game/requirements.rpy", 125], "oliganghangout": ["game/requirements.rpy", 127], "abbiehomework": ["game/requirements.rpy", 147], "lanacraft": ["game/requirements.rpy", 130], "clairestudy": ["game/requirements.rpy", 131], "engelstudy": ["game/requirements.rpy", 132], "bubblestudy": ["game/requirements.rpy", 133], "popularfriends": ["game/requirements.rpy", 134], "warning1": ["game/requirements.rpy", 136], "warning2": ["game/requirements.rpy", 137], "warning3": ["game/requirements.rpy", 138], "warning4": ["game/requirements.rpy", 139], "warning5": ["game/requirements.rpy", 140], "sciencetest": ["game/requirements.rpy", 142], "abbiemeandefend": ["game/requirements.rpy", 144], "abbieteach": ["game/requirements.rpy", 145], "abbiehelp": ["game/requirements.rpy", 146], "oligangtry": ["game/requirements.rpy", 149], "oligangjoin": ["game/requirements.rpy", 150], "populartiktok": ["game/requirements.rpy", 152], "populartiktoklater": ["game/requirements.rpy", 153], "askedcircle": ["game/requirements.rpy", 155], "askedthavel": ["game/requirements.rpy", 156], "askedbloomie": ["game/requirements.rpy", 157], "circleinvite": ["game/requirements.rpy", 159], "thavelinvite": ["game/requirements.rpy", 160], "bloomieinvite": ["game/requirements.rpy", 161], "emilyinvite": ["game/requirements.rpy", 162], "demiinvite": ["game/requirements.rpy", 163], "sashainvite": ["game/requirements.rpy", 164], "claengbub": ["game/requirements.rpy", 168], "abblana": ["game/requirements.rpy", 169], "oligang": ["game/requirements.rpy", 170], "alone": ["game/requirements.rpy", 171], "clairesorry": ["game/requirements.rpy", 173], "clairebeatup": ["game/requirements.rpy", 174], "clairedefend": ["game/requirements.rpy", 175], "normalroute": ["game/requirements.rpy", 179], "ocroute": ["game/requirements.rpy", 180], "teacherroute": ["game/requirements.rpy", 181], "circlemad1": ["game/requirements.rpy", 184], "circlemad2": ["game/requirements.rpy", 185], "circlemad3": ["game/requirements.rpy", 186], "thavelmad1": ["game/requirements.rpy", 188], "thavelmad2": ["game/requirements.rpy", 189], "thavelmad3": ["game/requirements.rpy", 190], "bloomiemad1": ["game/requirements.rpy", 192], "bloomiemad2": ["game/requirements.rpy", 193], "bloomiemad3": ["game/requirements.rpy", 194], "mc": ["game/script.rpy", 3], "x": ["game/script.rpy", 4], "c": ["game/script.rpy", 8], "e": ["game/script.rpy", 9], "b": ["game/script.rpy", 10], "l": ["game/script.rpy", 11], "a": ["game/script.rpy", 12], "o": ["game/script.rpy", 13], "z": ["game/script.rpy", 14], "ed": ["game/script.rpy", 15], "p": ["game/script.rpy", 16], "lz": ["game/script.rpy", 17], "cb": ["game/script.rpy", 18], "kv": ["game/script.rpy", 19], "rb": ["game/script.rpy", 20], "ri": ["game/script.rpy", 21], "ru": ["game/script.rpy", 22], "sk": ["game/script.rpy", 23], "al": ["game/script.rpy", 24], "msc": ["game/script.rpy", 28], "mst": ["game/script.rpy", 29], "msb": ["game/script.rpy", 30], "mse": ["game/script.rpy", 31], "msg": ["game/script.rpy", 32], "msd": ["game/script.rpy", 33], "mss": ["game/script.rpy", 34], "mscl": ["game/script.rpy", 35], "msa": ["game/script.rpy", 36], "msso": ["game/script.rpy", 37], "msac": ["game/script.rpy", 38], "msl": ["game/script.rpy", 39], "msw": ["game/script.rpy", 40], "msx": ["game/script.rpy", 41], "msh": ["game/script.rpy", 42], "d": ["game/script.rpy", 46], "q": ["game/script.rpy", 47], "yi": ["game/script.rpy", 48], "ya": ["game/script.rpy", 49], "sp": ["game/script.rpy", 50], "tm": ["game/script.rpy", 51], "n": ["game/script.rpy", 52], "j": ["game/script.rpy", 53], "k": ["game/script.rpy", 54], "m": ["game/script.rpy", 55], "py": ["game/script.rpy", 56], "ca": ["game/script.rpy", 57], "ja": ["game/script.rpy", 58], "ma": ["game/script.rpy", 59], "jac": ["game/script.rpy", 60], "no": ["game/script.rpy", 61], "oc": ["game/script.rpy", 62], "xx": ["game/script.rpy", 64], "ju": ["game/script.rpy", 65], "pe": ["game/script.rpy", 66]}, "screen": {"say": ["game/screens.rpy", 98], "input": ["game/screens.rpy", 174], "choice": ["game/screens.rpy", 207], "quick_menu": ["game/screens.rpy", 1449], "navigation": ["game/screens.rpy", 298], "main_menu": ["game/screens.rpy", 363], "game_menu": ["game/screens.rpy", 449], "about": ["game/screens.rpy", 574], "save": ["game/screens.rpy", 614], "load": ["game/screens.rpy", 621], "file_slots": ["game/screens.rpy", 628], "preferences": ["game/screens.rpy", 743], "history": ["game/screens.rpy", 910], "help": ["game/screens.rpy", 1000], "keyboard_help": ["game/screens.rpy", 1029], "mouse_help": ["game/screens.rpy", 1080], "gamepad_help": ["game/screens.rpy", 1103], "confirm": ["game/screens.rpy", 1169], "skip_indicator": ["game/screens.rpy", 1232], "notify": ["game/notification.rpy", 1], "nvl": ["game/screens.rpy", 1327], "nvl_dialogue": ["game/screens.rpy", 1359], "finish_animating_achievement": ["game/achievement_backend.rpy", 485], "achievement_popup": ["game/achievements.rpy", 536], "achievement_gallery": ["game/achievements.rpy", 600], "countdown": ["game/text.rpy", 802]}, "transform": {"dissolvein": ["game/screens.rpy", 294], "delayed_blink": ["game/screens.rpy", 1250], "notify_appear": ["game/screens.rpy", 1299], "achievement_popout": ["game/achievements.rpy", 578], "happy": ["game/emotions.rpy", 1], "worried": ["game/emotions.rpy", 10], "appearleft": ["game/emotions.rpy", 20], "appearright": ["game/emotions.rpy", 28], "alpha_dissolve": ["game/script.rpy", 69], "credit": ["game/emotions.rpy", 43], "chromatic_offset": ["game/text.rpy", 809]}, "callable": {"get_random_screen_tag": ["game/achievement_backend.rpy", 24], "Achievement.__init__": ["game/achievement_backend.rpy", 88], "Achievement.get_timestamp": ["game/achievement_backend.rpy", 125], "Achievement.add_progress": ["game/achievement_backend.rpy", 202], "Achievement.clear": ["game/achievement_backend.rpy", 209], "Achievement.get_progress": ["game/achievement_backend.rpy", 213], "Achievement.grant": ["game/achievement_backend.rpy", 217], "Achievement.has": ["game/achievement_backend.rpy", 236], "Achievement.progress": ["game/achievement_backend.rpy", 240], "Achievement.achievement_popup": ["game/achievement_backend.rpy", 257], "Achievement.AddProgress": ["game/achievement_backend.rpy", 287], "Achievement.Progress": ["game/achievement_backend.rpy", 291], "Achievement.Toggle": ["game/achievement_backend.rpy", 295], "Achievement.Grant": ["game/achievement_backend.rpy", 305], "LinkedAchievement.__init__": ["game/achievement_backend.rpy", 364], "LinkedAchievement.__call__": ["game/achievement_backend.rpy", 402], "touch": ["game/gui.rpy", 420], "small": ["game/gui.rpy", 427], "DispTextStyle.__init__": ["game/text.rpy", 21], "DispTextStyle.add_tags": ["game/text.rpy", 25], "DispTextStyle.apply_style": ["game/text.rpy", 42], "DispTextStyle.start_tags": ["game/text.rpy", 53], "DispTextStyle.end_tags": ["game/text.rpy", 72], "BounceText.__init__": ["game/text.rpy", 88], "BounceText.render": ["game/text.rpy", 103], "BounceText.event": ["game/text.rpy", 125], "BounceText.visit": ["game/text.rpy", 128], "FadeInText.__init__": ["game/text.rpy", 135], "FadeInText.render": ["game/text.rpy", 150], "FadeInText.visit": ["game/text.rpy", 169], "ScareText.__init__": ["game/text.rpy", 174], "ScareText.render": ["game/text.rpy", 182], "ScareText.visit": ["game/text.rpy", 195], "ChaosText.__init__": ["game/text.rpy", 210], "ChaosText.render": ["game/text.rpy", 219], "ChaosText.visit": ["game/text.rpy", 256], "RotateText.__init__": ["game/text.rpy", 261], "RotateText.render": ["game/text.rpy", 268], "RotateText.visit": ["game/text.rpy", 284], "SwapText.__init__": ["game/text.rpy", 346], "SwapText.render": ["game/text.rpy", 363], "SwapText.visit": ["game/text.rpy", 386], "MoveText.__init__": ["game/text.rpy", 395], "MoveText.render": ["game/text.rpy", 402], "MoveText.event": ["game/text.rpy", 424], "MoveText.visit": ["game/text.rpy", 429], "bounce_tag": ["game/text.rpy", 444], "fade_in_tag": ["game/text.rpy", 498], "scare_tag": ["game/text.rpy", 537], "chaos_tag": ["game/text.rpy", 565], "rotate_tag": ["game/text.rpy", 584], "swap_tag": ["game/text.rpy", 619], "move_tag": ["game/text.rpy", 645], "paragraph_tag": ["game/text.rpy", 672], "omega_tag": ["game/text.rpy", 694], "glitch": ["game/text.rpy", 819]}}, "build": {"directory_name": "fpn-FULLY_RECRAFTED", "executable_name": "fpn", "include_update": false, "packages": [{"name": "gameonly", "formats": ["null"], "file_lists": ["all"], "description": "Game-Only Update for Mobile", "update": true, "dlc": false, "hidden": true}, {"name": "pc", "formats": ["zip"], "file_lists": ["windows", "linux", "renpy", "all"], "description": "PC: Windows and Linux", "update": true, "dlc": false, "hidden": false}, {"name": "linux", "formats": ["tar.bz2"], "file_lists": ["linux", "linux_arm", "renpy", "all"], "description": "Linux", "update": true, "dlc": false, "hidden": false}, {"name": "mac", "formats": ["app-zip", "app-dmg"], "file_lists": ["mac", "renpy", "all"], "description": "Macintosh", "update": true, "dlc": false, "hidden": false}, {"name": "win", "formats": ["zip"], "file_lists": ["windows", "renpy", "all"], "description": "Windows", "update": true, "dlc": false, "hidden": false}, {"name": "market", "formats": ["bare-zip"], "file_lists": ["windows", "linux", "mac", "renpy", "all"], "description": "Windows, Mac, Linux for Markets", "update": true, "dlc": false, "hidden": false}, {"name": "steam", "formats": ["zip"], "file_lists": ["windows", "linux", "mac", "renpy", "all"], "description": "steam", "update": true, "dlc": false, "hidden": true}, {"name": "android", "formats": ["directory"], "file_lists": ["android", "all"], "description": "android", "update": false, "dlc": true, "hidden": true}, {"name": "ios", "formats": ["directory"], "file_lists": ["ios", "all"], "description": "ios", "update": false, "dlc": true, "hidden": true}, {"name": "web", "formats": ["zip"], "file_lists": ["web", "renpy", "all"], "description": "web", "update": false, "dlc": true, "hidden": true}], "archives": [["archive", ["all"]]], "documentation_patterns": ["*.html", "*.txt"], "base_patterns": [["*.py", null], ["*.sh", null], ["*.app/", null], ["*.dll", null], ["*.manifest", null], ["*.keystore", null], ["**.rpe.py", null], ["update.pem", null], ["lib/", null], ["renpy/", null], ["update/", null], ["common/", null], ["update/", null], ["old-game/", null], ["base/", null], ["icon.ico", null], ["icon.icns", null], ["project.json", null], ["log.txt", null], ["errors.txt", null], ["traceback.txt", null], ["image_cache.txt", null], ["text_overflow.txt", null], ["dialogue.txt", null], ["dialogue.tab", null], ["profile_screen.txt", null], ["files.txt", null], ["memory.txt", null], ["tmp/", null], ["game/saves/", null], ["game/bytecode.rpyb", null], ["archived/", null], ["launcherinfo.py", null], ["android.txt", null], ["game/presplash*.*", ["all"]], ["android.json", ["android"]], [".android.json", ["android"]], ["android-*.png", ["android"]], ["android-*.jpg", ["android"]], ["ouya_icon.png", null], ["ios-presplash.*", ["ios"]], ["ios-launchimage.png", null], ["ios-icon.png", null], ["web-presplash.png", ["web"]], ["web-presplash.jpg", ["web"]], ["web-presplash.webp", ["web"]], ["web-icon.png", ["web"]], ["progressive_download.txt", ["web"]], ["steam_appid.txt", null], ["game/cache/bytecode-312.rpyb", ["all"]], ["game/cache/bytecode-*.rpyb", null], ["game/cache/build_info.json", null], ["game/cache/build_time.txt", null], ["**~", null], ["**.bak", null], ["**/.**", null], ["**/#**", null], ["**/thumbs.db", null], [".*", null], ["**", ["all"]]], "renpy_patterns": [["renpy/common/_compat/**", null], ["renpy/common/_roundrect/**", null], ["renpy/common/_outline/**", null], ["renpy/common/_theme**", null], ["renpy/**__pycache__/**.cpython-312.pyc", ["all"]], ["renpy/**__pycache__", ["all"]], ["**~", null], ["**/#*", null], ["**/.*", null], ["**.old", null], ["**.new", null], ["**.rpa", null], ["**.rpe", null], ["**.rpe.py", null], ["**/steam_appid.txt", null], ["renpy.py", ["all"]], ["renpy/", ["all"]], ["renpy/**.py", ["renpy"]], ["renpy/**.pxd", null], ["renpy/**.pxi", null], ["renpy/**.pyx", null], ["renpy/**.pyc", null], ["renpy/**.pyo", null], ["renpy/common/", ["all"]], ["renpy/common/_compat/**", ["renpy"]], ["renpy/common/**.rpy", ["renpy"]], ["renpy/common/**.rpym", ["renpy"]], ["renpy/common/_compat/**", ["renpy"]], ["renpy/common/**", ["all"]], ["renpy/**", ["all"]], ["lib/*/renpy", null], ["lib/*/renpy.exe", null], ["lib/*/pythonw.exe", null], ["lib/py2-*/", null], ["lib/py*-windows-i686/**", ["windows_i686"]], ["lib/py*-windows-x86_64/**", ["windows"]], ["lib/py*-linux-i686/**", ["linux_i686"]], ["lib/py*-linux-aarch64/**", ["linux_arm"]], ["lib/py*-linux-armv7l/**", ["linux_arm"]], ["lib/py*-linux-*/**", ["linux"]], ["lib/py*-mac-*/**", ["mac"]], ["lib/web/**", ["web"]], ["lib/python2.*/**", null], ["lib/**", ["windows", "linux", "mac", "android", "ios"]], ["renpy.sh", ["linux", "mac"]]], "xbit_patterns": ["**.sh", "lib/py*-linux-*/*", "lib/py*-mac-*/*", "**.app/Contents/MacOS/*"], "version": "FULLY_RECRAFTED", "display_name": "Fundamental Paper Novel", "exclude_empty_directories": true, "allow_integrated_gpu": true, "renpy": false, "script_version": true, "destination": "fpn-FULLY_RECRAFTED-dists", "itch_channels": {"*-all.zip": "win-osx-linux", "*-market.zip": "win-osx-linux", "*-pc.zip": "win-linux", "*-win.zip": "win", "*-mac.zip": "osx", "*-linux.tar.bz2": "linux", "*-release.apk": "android"}, "mac_info_plist": {}, "merge": [["linux_i686", "linux"], ["windows_i686", "windows"]], "include_i686": true, "change_icon_i686": true, "android_permissions": [], "_sdk_fonts": false, "update_formats": ["rpu"], "info": {"info": {}, "time": 1772666837.760138, "name": "Fundamental Paper Novel", "version": "FULLY_RECRAFTED"}}, "test": {"has_default_testcase": false}}